bore/__init__.py
bore/base.py
bore/data.py
bore/decorators.py
bore/math.py
bore/mixins.py
bore/models.py
bore/optimizers/__init__.py
bore/optimizers/base.py
bore/optimizers/utils.py
bore/optimizers/svgd/__init__.py
bore/optimizers/svgd/base.py
bore/optimizers/svgd/kernels.py
bore/plugins/__init__.py
bore/plugins/hpbandster/__init__.py
bore/plugins/hpbandster/base.py
bore/plugins/hpbandster/multi_fidelity.py
bore/plugins/hpbandster/types.py
bore/utils/__init__.py
bore/utils/deduplicate.py
bore-1.5.0.dist-info/AUTHORS.rst
bore-1.5.0.dist-info/LICENSE
bore-1.5.0.dist-info/METADATA
bore-1.5.0.dist-info/WHEEL
bore-1.5.0.dist-info/top_level.txt
bore-1.5.0.dist-info/RECORD
