Metadata-Version: 2.1
Name: bore
Version: 1.5.0
Summary: Bayesian Optimization by Density-Ratio Estimation
Home-page: https://github.com/ltiao/bore
Author: Louis C. Tiao
Author-email: louistiao@gmail.com
License: MIT license
Keywords: bore
Platform: UNKNOWN
Classifier: Development Status :: 2 - Pre-Alpha
Classifier: Intended Audience :: Developers
Classifier: License :: OSI Approved :: MIT License
Classifier: Natural Language :: English
Classifier: Programming Language :: Python :: 3
Classifier: Programming Language :: Python :: 3.5
Classifier: Programming Language :: Python :: 3.6
Classifier: Programming Language :: Python :: 3.7
Classifier: Programming Language :: Python :: 3.8
Requires-Python: >=3.5
License-File: LICENSE
License-File: AUTHORS.rst
Requires-Dist: numpy (==1.20.3)
Requires-Dist: scipy (==1.7.0)
Requires-Dist: Cython (==0.29.23)
Requires-Dist: ConfigSpace (==0.4.18)
Provides-Extra: hpbandster
Requires-Dist: hpbandster (==0.7.4) ; extra == 'hpbandster'
Provides-Extra: tf
Requires-Dist: tensorflow (==2.5.0) ; extra == 'tf'
Provides-Extra: tf-gpu
Requires-Dist: tensorflow-gpu (==2.5.0) ; extra == 'tf-gpu'
